testifyr/__about__.py
testifyr/__init__.py
testifyr/_elements.py
testifyr/_stuff.py
testifyr/_templates.py
testifyr/_utils.py
testifyr/elements.py
testifyr/stuff.py
testifyr/templates/space.html
testifyr/testify/__init__.py
testifyr/testify/__main__.py
testifyr/testify/_convert_utils.py
testifyr/testify/testify.py
testifyr/testify/testifyr.css
testifyr/testify/Templates/exam/conf.json
testifyr/testify/Templates/exam/index.html.j2
testifyr-0.0.2.dist-info/METADATA
testifyr-0.0.2.dist-info/WHEEL
testifyr-0.0.2.dist-info/RECORD
